{"id":220,"cname":"用户名称1","datetime":"2015-08-29 13:35:59","message":"/hsmile"},{"id":220,"cname":"用户名称1","datetime":"2015-08-29 13:37:05","message":"/88"},{"id":220,"cname":"用户名称1","datetime":"2015-08-29 13:37:15","message":"/bomb"},{"id":220,"cname":"用户名称1","datetime":"2015-08-29 13:45:40","message":"/idwtsy"},{"id":220,"cname":"用户名称1","datetime":"2015-08-29 13:45:43","message":"fds "},{"id":220,"cname":"用户名称1","datetime":"2015-08-29 16:04:26","message":"/88"},{"id":220,"cname":"用户名称1","datetime":"2015-08-29 16:04:31","message":"范德萨范德萨"},